MANIFEST.in
requirements-test.txt
requirements.txt
setup.py
reinforce/__init__.py
reinforce/rl.py
reinforce/test.py
reinforce/xo.py
reinforce_toolkit.egg-info/PKG-INFO
reinforce_toolkit.egg-info/SOURCES.txt
reinforce_toolkit.egg-info/dependency_links.txt
reinforce_toolkit.egg-info/not-zip-safe
reinforce_toolkit.egg-info/top_level.txt