Metadata-Version: 1.1
Name: reinforce-toolkit
Version: 0.2.1
Summary: A simple Python reinforcement learning library.
Home-page: https://github.com/chrisspen/reinforce
Author: Chris Spencer
Author-email: chrisspen@gmail.com
License: LGPL License
Platform: UNKNOWN
Classifier: Development Status :: 4 - Beta
Classifier: Intended Audience :: Developers
Classifier: License :: OSI Approved :: GNU Lesser General Public License v3 (LGPLv3)
Classifier: Operating System :: OS Independent
Classifier: Programming Language :: Python
Classifier: Programming Language :: Python :: 2.7
Classifier: Programming Language :: Python :: 3.5
